mds_account_pos_movelines-0.1.2.dist-info/DESCRIPTION.rst
mds_account_pos_movelines-0.1.2.dist-info/METADATA
mds_account_pos_movelines-0.1.2.dist-info/RECORD
mds_account_pos_movelines-0.1.2.dist-info/WHEEL
mds_account_pos_movelines-0.1.2.dist-info/entry_points.txt
mds_account_pos_movelines-0.1.2.dist-info/metadata.json
mds_account_pos_movelines-0.1.2.dist-info/top_level.txt
trytond/modules/account_pos_movelines/README.rst
trytond/modules/account_pos_movelines/__init__.py
trytond/modules/account_pos_movelines/account.py
trytond/modules/account_pos_movelines/account.xml
trytond/modules/account_pos_movelines/icon.xml
trytond/modules/account_pos_movelines/sqlfunction.py
trytond/modules/account_pos_movelines/tryton.cfg
trytond/modules/account_pos_movelines/versiondep.txt
trytond/modules/account_pos_movelines/icon/buchcol.svg
trytond/modules/account_pos_movelines/locale/de_DE.po
trytond/modules/account_pos_movelines/view/movelines_form.xml
trytond/modules/account_pos_movelines/view/movelines_tree.xml
