Metadata-Version: 2.0
Name: mds-account-pos-movelines
Version: 0.1.2
Summary: Tryton module to show move lines
Home-page: https://www.m-ds.de/
Author: m-ds GmbH
Author-email: service@m-ds.de
License: GPL-3
Download-URL: https://www.m-ds.de/serviceportal/downloads/trytonmodul-account-pos-movelines
Keywords: tryton sale account move journal
Platform: UNKNOWN
Classifier: Development Status :: 5 - Production/Stable
Classifier: Environment :: Plugins
Classifier: Framework :: Tryton
Classifier: Intended Audience :: Developers
Classifier: Intended Audience :: Customer Service
Classifier: Intended Audience :: Information Technology
Classifier: Intended Audience :: Financial and Insurance Industry
Classifier: Topic :: Office/Business
Classifier: Topic :: Office/Business :: Financial :: Accounting
Classifier: Natural Language :: German
Classifier: Natural Language :: English
Classifier: Operating System :: OS Independent
Classifier: License :: OSI Approved :: GNU General Public License (GPL)
Classifier: Programming Language :: Python :: 2.7
Requires-Dist: mds-sqlextension (>=0.1.2)
Requires-Dist: trytond (>=3.8,<3.9)
Requires-Dist: trytond-account (>=3.8,<3.9)
Requires-Dist: trytond-account-invoice (>=3.8,<3.9)
